rsssync/__init__.py
rsssync/__main__.py
rsssync/downloader.py
rsssync/main.py
rsssync/meta_refresh_downloader.py
rsssync/pls_downloader.py
RSSsync-0.1.dist-info/METADATA
RSSsync-0.1.dist-info/WHEEL
RSSsync-0.1.dist-info/entry_points.txt
RSSsync-0.1.dist-info/top_level.txt
RSSsync-0.1.dist-info/RECORD
