Metadata-Version: 2.1
Name: RSSsync
Version: 0.1
Summary: A feed aggregator reimagined as a file synchronizer
Author: dodopod
Author-email: dodopod@gmail.com
License: UNKNOWN
Platform: UNKNOWN
Requires-Python: >=3.6
Requires-Dist: feedparser
Requires-Dist: toml
Requires-Dist: pyxdg
